fastfeatures/__init__.py
fastfeatures/core/__init__.py
fastfeatures/core/generate_feature.py
fastfeatures/core/generate_project_scaffolding.py
fastfeatures/core/generate_settings.py
fastfeatures/core/models_discoverer.py
fastfeatures/core/routes_discoverer.py
fastfeatures/core/utils.py
fastfeatures/template_base/app/core/__init__.py
fastfeatures/template_base/app/core/lib/base_model_service.py
fastfeatures/template_base/app/core/lib/database.py
fastfeatures/template_base/app/features/__init__.py
fastfeatures/template_base/app/main.py
fastfeatures/template_base/env_template
fastfeatures/template_feature/__init__.py
fastfeatures/template_feature/models/__init__.py
fastfeatures/template_feature/models/feature_name.py
fastfeatures/template_feature/routes.py
fastfeatures/template_feature/services/__init__.py
fastfeatures/template_feature/services/feature_name_services.py
fastfeatures-0.1.6.dist-info/METADATA
fastfeatures-0.1.6.dist-info/WHEEL
fastfeatures-0.1.6.dist-info/entry_points.txt
fastfeatures-0.1.6.dist-info/licenses/LICENSE
fastfeatures-0.1.6.dist-info/RECORD
