Metadata-Version: 2.4
Name: fastfeatures
Version: 0.1.6
Summary: A powerful FastAPI toolkit designed to accelerate development with a modular, async-first architecture. It provides project scaffolding, feature generation, automatic settings from .env files, and auto-discovery of routes and SQL models. This reduces boilerplate, simplifies setup, and ensures high performance, ideal for modern applications and LLM integrations. Seamlessly integrates with Alembic for database migrations.
License-Expression: MIT
License-File: LICENSE
Author: Yuri Seki
Author-email: yuriseki@gmail.com
Requires-Python: >=3.10
Classifier: Programming Language :: Python :: 3
Classifier: License :: OSI Approved :: MIT License
Classifier: Operating System :: OS Independent
Requires-Dist: aiosqlite (>=0.21.0,<0.22.0)
Requires-Dist: alembic (>=1.17.1,<2.0.0)
Requires-Dist: asyncpg (>=0.30.0,<0.31.0)
Requires-Dist: click (>=8.1.7,<9.0.0)
Requires-Dist: fastapi (>=0.118.3,<0.119.0)
Requires-Dist: pydantic-settings (>=2.11.0,<3.0.0)
Requires-Dist: python-dotenv (>=1.0.0,<2.0.0)
Requires-Dist: setuptools (>=80.9.0,<90.0.0)
Requires-Dist: sqlalchemy (>=2.0.44,<3.0.0)
Requires-Dist: sqlmodel (>=0.0.27,<0.0.28)
Requires-Dist: uvicorn (>=0.38.0,<0.39.0)
Project-URL: Homepage, https://github.com/yuriseki/fastfeatures
Project-URL: Issues, https://github.com/yuriseki/fastfeatures/issues
